pymementodb/__init__.py
pymementodb/__version__.py
pymementodb/entry.py
pymementodb/exception.py
pymementodb/field.py
pymementodb/helpers.py
pymementodb/library.py
pymementodb-1.0.2.dist-info/licenses/LICENSE
test/__init__.py
test/test_entry.py
test/test_field.py
test/test_library.py
test/test_memento.py
pymementodb-1.0.2.dist-info/METADATA
pymementodb-1.0.2.dist-info/WHEEL
pymementodb-1.0.2.dist-info/top_level.txt
pymementodb-1.0.2.dist-info/RECORD
