Metadata-Version: 2.4
Name: pymementodb
Version: 1.0.2
Summary: Memento Database Python SDK
Home-page: https://gitlab.com/pavloglushko/pymementodb
Download-URL: https://gitlab.com/pavloglushko/pymementodb/-/archive/v1.0.2/pymementodb-v1.0.2.tar.gz
Author: Pavlo Glushko
Author-email: pavloglushko@gmail.com
License: MIT
Project-URL: Source, https://gitlab.com/pavloglushko/pymementodb
Classifier: Intended Audience :: Developers
Classifier: Natural Language :: English
Classifier: Operating System :: OS Independent
Classifier: Programming Language :: Python
Classifier: Programming Language :: Python :: 3.10
Classifier: Topic :: Software Development :: Libraries :: Python Modules
License-File: LICENSE
Requires-Dist: requests>=2.28.1
Dynamic: author
Dynamic: author-email
Dynamic: classifier
Dynamic: description
Dynamic: description-content-type
Dynamic: download-url
Dynamic: home-page
Dynamic: license
Dynamic: license-file
Dynamic: project-url
Dynamic: requires-dist
Dynamic: summary
